README.md
setup.py
fib_py/__init__.py
fib_py/version.py
fib_py.egg-info/PKG-INFO
fib_py.egg-info/SOURCES.txt
fib_py.egg-info/dependency_links.txt
fib_py.egg-info/entry_points.txt
fib_py.egg-info/requires.txt
fib_py.egg-info/top_level.txt
fib_py/cmd/__init__.py
fib_py/cmd/fib_num.py
fib_py/fib_calcs/__init__.py
fib_py/fib_calcs/fib_num.py
fib_py/fib_calcs/fib_nums.py
tests/fib_py/__init__.py
tests/fib_py/fib_calcs/__init__.py
tests/fib_py/fib_calcs/test_fib_number.py
tests/fib_py/fib_calcs/test_fib_numbers.py